paca/__init__.py
paca/paca.py
paca-0.1.0.dist-info/LICENSE.txt
paca-0.1.0.dist-info/METADATA
paca-0.1.0.dist-info/WHEEL
paca-0.1.0.dist-info/entry_points.txt
paca-0.1.0.dist-info/top_level.txt
paca-0.1.0.dist-info/RECORD
