Metadata-Version: 2.1
Name: paca
Version: 0.1.0
Summary: Check asset status using Alpaca Broker API
Home-page: https://github.com/rgomezjnr/paca
Author: Robert Gomez, Jr.
Author-email: rgomezjnr@gmail.com
License: MIT
Keywords: alpaca broker api asset stock market crypto trading finace investment python cli tool script
Platform: UNKNOWN
Classifier: Programming Language :: Python :: 3
Classifier: Programming Language :: Python :: 3.7
Classifier: Programming Language :: Python :: 3.8
Classifier: License :: OSI Approved :: MIT License
Classifier: Operating System :: OS Independent
Classifier: Development Status :: 4 - Beta
Classifier: Environment :: Console
Classifier: Intended Audience :: End Users/Desktop
Classifier: Intended Audience :: Financial and Insurance Industry
Classifier: Natural Language :: English
Classifier: Topic :: Internet
Classifier: Topic :: Utilities
Classifier: Topic :: Office/Business :: Financial :: Investment
Requires-Python: >=3.6
Requires-Dist: alpaca-trade-api
Requires-Dist: colorama
